dippy/__init__.py
dippy/__main__.py
dippy/client.py
dippy/config/__init__.py
dippy/config/factory.py
dippy/config/json_loader.py
dippy/config/loader.py
dippy/config/yaml_loader.py
dippy/events.py
dippy/extensions/__init__.py
dippy/extensions/command.py
dippy/extensions/extension.py
dippy/extensions/extension_manager.py
dippy/extensions/listener.py
dippy/extensions/registry.py
dippy/labels/__init__.py
dippy/labels/config_model.py
dippy/labels/memory_storage.py
dippy/labels/sqlalchemy_storage.py
dippy/labels/storage.py
dippy/logging.py
dippy/sqlalchemy_connector.py
dippy/utils/missing_module.py
dippy.bot-0.1.1a28.dist-info/WHEEL
dippy.bot-0.1.1a28.dist-info/METADATA
dippy.bot-0.1.1a28.dist-info/RECORD
